followeraudit/FauditAPIclient.py
followeraudit/FauditException.py
followeraudit/__init__.py
followeraudit/config.py
followerauditapi-0.0.8.dist-info/LICENSE
followerauditapi-0.0.8.dist-info/METADATA
followerauditapi-0.0.8.dist-info/WHEEL
followerauditapi-0.0.8.dist-info/top_level.txt
followerauditapi-0.0.8.dist-info/RECORD
