Metadata-Version: 2.1
Name: followerauditapi
Version: 0.0.8
Summary: Python library to access followeraudit API
Home-page: https://github.com/bytesview/followerauditapi-python
Author: Followeraudit
Author-email: contact@followeraudit.com
License: GNU V3
Keywords: followerauditapi,newaudit,bulkaudit,getaudit
Platform: UNKNOWN
Classifier: Development Status :: 5 - Production/Stable
Classifier: Intended Audience :: Developers
Classifier: Intended Audience :: Customer Service
Classifier: License :: OSI Approved :: GNU General Public License v3 (GPLv3)
Classifier: Programming Language :: Python :: 3.5
Classifier: Programming Language :: Python :: 3.6
Classifier: Programming Language :: Python :: 3.7
Classifier: Programming Language :: Python :: 3.8
Classifier: Programming Language :: Python :: 3.9
Classifier: Programming Language :: Python :: 3.10
Requires-Python: >=3.5
Requires-Dist: requests (<3.0.0)
